combine_gtfs_feeds/.vscode/launch.json
combine_gtfs_feeds/__init__.py
combine_gtfs_feeds/cli/__init__.py
combine_gtfs_feeds/cli/cli.py
combine_gtfs_feeds/cli/gtfs_schema.py
combine_gtfs_feeds/cli/log_controller.py
combine_gtfs_feeds/cli/main.py
combine_gtfs_feeds/cli/run.py
combine_gtfs_feeds/test.py
combine_gtfs_feeds-0.1.9.dist-info/LICENSE
combine_gtfs_feeds-0.1.9.dist-info/METADATA
combine_gtfs_feeds-0.1.9.dist-info/WHEEL
combine_gtfs_feeds-0.1.9.dist-info/RECORD
