Metadata-Version: 2.3
Name: combine-gtfs-feeds
Version: 0.1.9
Summary: CLI tool to combine multiple GTFS feeds.
License: MIT
Author: stefancoe
Author-email: coestefan@gmail.com
Requires-Python: >=3.11
Classifier: License :: OSI Approved :: MIT License
Classifier: Programming Language :: Python :: 3
Classifier: Programming Language :: Python :: 3.11
Classifier: Programming Language :: Python :: 3.12
Classifier: Programming Language :: Python :: 3.13
Requires-Dist: numpy (>=1.24.1)
Requires-Dist: pandas (>=2.1.0)
Requires-Dist: pandera (>=0.5.0)
Requires-Dist: pyyaml (>=6.0)
